furiosa/registry/__init__.py
furiosa/registry/errors.py
furiosa/registry/git_version.txt
furiosa/registry/model.py
furiosa/registry/py.typed
furiosa/registry/utils.py
furiosa/registry/client/__init__.py
furiosa/registry/client/transport/__init__.py
furiosa/registry/client/transport/base.py
furiosa/registry/client/transport/file.py
furiosa/registry/client/transport/github.py
furiosa/registry/client/transport/http.py
furiosa/registry/client/transport/s3.py
furiosa_registry-0.9.1.dist-info/WHEEL
furiosa_registry-0.9.1.dist-info/METADATA
furiosa_registry-0.9.1.dist-info/RECORD
