Metadata-Version: 2.1
Name: furiosa-registry
Version: 0.9.1
Summary: FuriosaAI model registry
Author-email: "FurioaAI, Inc." <pkg@furiosa.ai>
Requires-Python: ~=3.8
Classifier: Development Status :: 4 - Beta
Classifier: Environment :: Console
Classifier: Intended Audience :: Developers
Classifier: Intended Audience :: System Administrators
Classifier: License :: OSI Approved :: Apache Software License
Classifier: Programming Language :: Python :: 3
Classifier: Programming Language :: Python :: 3.8
Classifier: Programming Language :: Python :: 3.9
Classifier: Programming Language :: Python :: 3.10
Classifier: Topic :: Software Development :: Libraries :: Python Modules
Classifier: Topic :: Scientific/Engineering :: Artificial Intelligence
Requires-Dist: PyYAML
Requires-Dist: aiofiles
Requires-Dist: aiohttp ~= 3.8.3
Requires-Dist: multipledispatch
Requires-Dist: pydantic
Requires-Dist: toml
Requires-Dist: tqdm
Requires-Dist: boto3 ; extra == "s3"
Requires-Dist: aioboto3 ; extra == "s3"
Requires-Dist: moto[s3] ; extra == "s3"
Requires-Dist: botocore ; extra == "s3"
Requires-Dist: pytest ; extra == "test"
Requires-Dist: pytest-aiohttp ; extra == "test"
Requires-Dist: pytest-asyncio ~= 0.17.2 ; extra == "test"
Requires-Dist: types-aiofiles ; extra == "test"
Requires-Dist: types-toml ; extra == "test"
Requires-Dist: types-PyYAML ; extra == "test"
Project-URL: Bug Tracker, https://github.com/furiosa-ai/furiosa-sdk/issues
Project-URL: Documentation, https://furiosa-ai.github.io/docs
Project-URL: Home, https://furiosa.ai
Project-URL: Source Code, https://github.com/furiosa-ai/furiosa-sdk
Provides-Extra: s3
Provides-Extra: test
